source_parser/__init__.py
source_parser/_version.py
source_parser/deduper.py
source_parser/helpers.py
source_parser/languages.yml
source_parser/utils.py
source_parser/cli/__init__.py
source_parser/cli/crawler.py
source_parser/cli/licenses.py
source_parser/cli/observers.py
source_parser/cli/repo_parse.py
source_parser/cli/repo_scrape.py
source_parser/cli/utils.py
source_parser/langtools/__init__.py
source_parser/langtools/javascript.py
source_parser/langtools/python.py
source_parser/parsers/__init__.py
source_parser/parsers/commentutils.py
source_parser/parsers/cpp_parser.py
source_parser/parsers/csharp_parser.py
source_parser/parsers/go_parser.py
source_parser/parsers/java_parser.py
source_parser/parsers/javascript_parser.py
source_parser/parsers/jsts_parser.py
source_parser/parsers/language_parser.py
source_parser/parsers/python_parser.py
source_parser/parsers/ruby_parser.py
source_parser/tree_sitter/__init__.py
source_parser/tree_sitter/config.py
source_parser/tree_sitter/assets/tree-sitter-bash/.eslintrc.js
source_parser/tree_sitter/assets/tree-sitter-bash/.git
source_parser/tree_sitter/assets/tree-sitter-bash/.gitattributes
source_parser/tree_sitter/assets/tree-sitter-bash/.gitignore
source_parser/tree_sitter/assets/tree-sitter-bash/.npmignore
source_parser/tree_sitter/assets/tree-sitter-bash/Cargo.toml
source_parser/tree_sitter/assets/tree-sitter-bash/LICENSE
source_parser/tree_sitter/assets/tree-sitter-bash/Package.swift
source_parser/tree_sitter/assets/tree-sitter-bash/README.md
source_parser/tree_sitter/assets/tree-sitter-bash/appveyor.yml
source_parser/tree_sitter/assets/tree-sitter-bash/binding.gyp
source_parser/tree_sitter/assets/tree-sitter-bash/grammar.js
source_parser/tree_sitter/assets/tree-sitter-bash/package.json
source_parser/tree_sitter/assets/tree-sitter-bash/.github/workflows/ci.yml
source_parser/tree_sitter/assets/tree-sitter-bash/.github/workflows/fuzz.yml
source_parser/tree_sitter/assets/tree-sitter-bash/.github/workflows/lint.yml
source_parser-1.2.0.dist-info/LICENSE
source_parser-1.2.0.dist-info/METADATA
source_parser-1.2.0.dist-info/WHEEL
source_parser-1.2.0.dist-info/entry_points.txt
source_parser-1.2.0.dist-info/top_level.txt
source_parser-1.2.0.dist-info/RECORD
