Metadata-Version: 2.1
Name: source-parser
Version: 1.2.0
Summary: Parsers and tools for extracting method/class-level features from source code
Home-page: https://github.com/microsoft/source_parser
Author: Microsoft
Author-email: vsdatascience@microsoft.com
Keywords: tree_sitter universal-ast codesearchnet method-docstring
Classifier: Development Status :: 4 - Beta
Classifier: Intended Audience :: Developers
Classifier: License :: OSI Approved :: MIT License
Classifier: Programming Language :: Python :: 3.8
Classifier: Programming Language :: Python :: 3.9
Classifier: Programming Language :: Python :: 3.10
Classifier: Programming Language :: Python :: 3.11
Requires-Python: >=3.8
License-File: LICENSE
Requires-Dist: autopep8 >=1.4.4
Requires-Dist: lz4 >=3.1.0
Requires-Dist: networkx >=2.5.1
Requires-Dist: datasketch >=1.5.3
Requires-Dist: tree-sitter <0.22,>=0.20.1
Requires-Dist: ray >=1.0.0
Requires-Dist: psutil >=5.6.3
Requires-Dist: tqdm >=4.36.1
Requires-Dist: columnize >=0.3.10
